slackutils/__init__.py
slackutils/_shared.py
slackutils/conversations.py
slackutils/users.py
slackutils-0.0.4.dist-info/METADATA
slackutils-0.0.4.dist-info/RECORD
slackutils-0.0.4.dist-info/WHEEL
slackutils-0.0.4.dist-info/top_level.txt
