Metadata-Version: 2.1
Name: slackutils
Version: 0.0.4
Summary: A small library to simplify slack web API calls
Home-page: https://github.com/madsWilthil/slackutils
Author: Mads Wilthil
Author-email: mads.wilthil@gmail.com
License: UNKNOWN
Platform: UNKNOWN
Classifier: Programming Language :: Python :: 3
Classifier: License :: OSI Approved :: MIT License
Classifier: Operating System :: OS Independent
Requires-Dist: slackclient
